{"ALLUSERSPROFILE":"C:\\ProgramData","ANDROID_HOME":"D:\\ProgramData\\Android\\Sdk","APPDATA":"C:\\Users\\HP\\AppData\\Roaming","BERRY_BIN_FOLDER":"C:\\Users\\HP\\AppData\\Local\\Temp\\xfs-162664ad","CHROME_CRASHPAD_PIPE_NAME":"\\\\.\\pipe\\crashpad_5872_KAMNHTLROBMEGWWC","COLORTERM":"truecolor","CommonProgramFiles":"C:\\Program Files\\Common Files","CommonProgramFiles(x86)":"C:\\Program Files (x86)\\Common Files","CommonProgramW6432":"C:\\Program Files\\Common Files","COMPUTERNAME":"DESKTOP-JVTSJ6I","ComSpec":"C:\\Windows\\system32\\cmd.exe","COREPACK_ROOT":"D:\\bin\\node\\windows\\node_modules\\corepack","DriverData":"C:\\Windows\\System32\\Drivers\\DriverData","FPS_BROWSER_APP_PROFILE_STRING":"Internet Explorer","FPS_BROWSER_USER_PROFILE_STRING":"Default","GIT_ASKPASS":"d:\\ProgramData\\Microsoft VS Code\\resources\\app\\extensions\\git\\dist\\askpass.sh","GRADLE_HOME":"C:\\Users\\HP\\AppData\\Local\\Temp\\.gradle","GRADLE_USER_HOME":"C:\\Users\\HP\\AppData\\Local\\Temp\\.gradle","HOMEDRIVE":"C:","HOMEPATH":"\\Users\\HP","INIT_CWD":"E:\\Repositories\\android-blog\\release-repo","IntelliJ IDEA Community Edition":"D:\\Program Files\\JetBrains\\IntelliJ IDEA Community Edition 2023.3.6\\bin;","JAVA_HOME":"D:\\bin\\java\\windows\\jdk-19","LANG":"en_US.UTF-8","LOCALAPPDATA":"C:\\Users\\HP\\AppData\\Local","LOGONSERVER":"\\\\DESKTOP-JVTSJ6I","MAVEN_HOME":"C:\\Users\\HP\\AppData\\Local\\Temp\\.m2","NODE_OPTIONS":"","npm_config_user_agent":"yarn/4.1.1 npm/? node/v18.18.0 win32 x64","npm_execpath":"C:\\Users\\HP\\AppData\\Local\\Temp\\xfs-162664ad\\yarn","npm_lifecycle_event":"postinstall","npm_node_execpath":"C:\\Users\\HP\\AppData\\Local\\Temp\\xfs-162664ad\\node","npm_package_json":"E:\\Repositories\\android-blog\\release-repo\\package.json","npm_package_name":"flowbite-react-admin-dashboard","npm_package_version":"1.0.0","NUMBER_OF_PROCESSORS":"4","OneDrive":"C:\\Users\\HP\\OneDrive","ORIGINAL_XDG_CURRENT_DESKTOP":"undefined","OS":"Windows_NT","PATH":"C:\\Users\\HP\\AppData\\Local\\Temp\\xfs-162664ad;C:\\Windows\\system32;C:\\Windows;C:\\Windows\\System32\\Wbem;C:\\Windows\\System32\\WindowsPowerShell\\v1.0\\;C:\\Windows\\System32\\OpenSSH\\;D:\\bin\\java\\windows\\jdk-19\\bin;D:\\bin\\git\\bin;D:\\bin\\node\\windows;C:\\cygwin64\\bin;C:\\Users\\HP\\AppData\\Local\\Microsoft\\WindowsApps;bin;node_modules\\.bin;C:\\Users\\HP\\AppData\\Local\\Programs\\Microsoft VS Code\\bin;D:\\Program Files\\JetBrains\\IntelliJ IDEA Community Edition 2023.3.6\\bin;;D:\\ProgramData\\Android\\Sdk\\platform-tools;D:\\ProgramData\\Android\\Sdk\\cmdline-tools\\latest\\bin;;E:\\Repositories\\android-blog\\release-repo\\node_modules\\.bin;E:\\Repositories\\android-blog\\release-repo\\bin","PATHEXT":".COM;.EXE;.BAT;.CMD;.VBS;.VBE;.JS;.JSE;.WSF;.WSH;.MSC","PROCESSOR_ARCHITECTURE":"AMD64","PROCESSOR_IDENTIFIER":"Intel64 Family 6 Model 78 Stepping 3, GenuineIntel","PROCESSOR_LEVEL":"6","PROCESSOR_REVISION":"4e03","ProgramData":"C:\\ProgramData","ProgramFiles":"C:\\Program Files","ProgramFiles(x86)":"C:\\Program Files (x86)","ProgramW6432":"C:\\Program Files","PROJECT_CWD":"E:\\Repositories\\android-blog\\release-repo","PROMPT":"$P$G","PSModulePath":"C:\\Program Files\\WindowsPowerShell\\Modules;C:\\Windows\\system32\\WindowsPowerShell\\v1.0\\Modules","PUBLIC":"C:\\Users\\Public","SESSIONNAME":"Console","SystemDrive":"C:","SystemRoot":"C:\\Windows","TEMP":"C:\\Users\\HP\\AppData\\Local\\Temp","TERM_PROGRAM":"vscode","TERM_PROGRAM_VERSION":"1.87.2","TMP":"C:\\Users\\HP\\AppData\\Local\\Temp","USERDOMAIN":"DESKTOP-JVTSJ6I","USERDOMAIN_ROAMINGPROFILE":"DESKTOP-JVTSJ6I","USERNAME":"HP","USERPROFILE":"C:\\Users\\HP","VSCODE_GIT_ASKPASS_EXTRA_ARGS":"","VSCODE_GIT_ASKPASS_MAIN":"d:\\ProgramData\\Microsoft VS Code\\resources\\app\\extensions\\git\\dist\\askpass-main.js","VSCODE_GIT_ASKPASS_NODE":"D:\\ProgramData\\Microsoft VS Code\\Code.exe","VSCODE_GIT_IPC_HANDLE":"\\\\.\\pipe\\vscode-git-d5f69d37cc-sock","windir":"C:\\Windows","ZES_ENABLE_SYSMAN":"1","__COMPAT_LAYER":"DetectorsAppHealth"}